[
  {
    "question": {
      "hasImg":false,
      "questionText": "Naannawa hojjii mija'a taasisuu jedhuu maal jechuudha?",
      "imgUrl": ""
    },
    "optionA": {
      "id": "1",
      "hasImg": false,
      "ImgUrl": "",
      "optionText": "Qulqullina eeguu"
    },
    "optionB": {
      "id": "2",
      "hasImg": false,
      "ImgUrl": "",
      "optionText": "Iddo hojii hawwachiisa taasisuu"
    },
    "optionC": {
      "id": "3",
      "hasImg": false,
      "ImgUrl": "",
      "optionText": " A fi B 'n deebiidha"
    },
    "optionD": {
      "id": "4",
      "hasImg": false,
      "ImgUrl": "",
      "optionText": "Deebii hinqabu"
    },
    "answer": "3"
  },
  {
    "question": {
      "hasImg":false,
      "questionText": "Ilaalcha fi hubannoo _____ irratti taasissuun balaa hirrisa",
      "imgUrl": ""
    },
    "optionA": {
      "id": "1",
      "hasImg": false,
      "ImgUrl": "",
      "optionText": "Maatii"
    },
    "optionB": {
      "id": "2",
      "hasImg": false,
      "ImgUrl": "",
      "optionText": "Daandii"
    },
    "optionC": {
      "id": "3",
      "hasImg": false,
      "ImgUrl": "",
      "optionText": "A fi B deebiidha"
    },
    "optionD": {
      "id": "4",
      "hasImg": false,
      "ImgUrl": "",
      "optionText": "Deebii hin jiru"
    },
    "answer": "2"
  },
  {
    "question": {
      "hasImg":false,
      "questionText": "Ga'umsa konkolaachisuu fooyyeefachuuf tatachuun?",
      "imgUrl": ""
    },
    "optionA": {
      "id": "1",
      "hasImg": false,
      "ImgUrl": "",
      "optionText": "Amala gaarii konkolachisaattii"
    },
    "optionB": {
      "id": "2",
      "hasImg": false,
      "ImgUrl": "",
      "optionText": "Amala ittisa balaatti"
    },
    "optionC": {
      "id": "3",
      "hasImg": false,
      "ImgUrl": "",
      "optionText": " A fi B deebiidha"
    },
    "optionD": {
      "id": "4",
      "hasImg": false,
      "ImgUrl": "",
      "optionText": "Deebii hin qabu"
    },
    "answer": "3"
  },
  {
    "question": {
      "hasImg":false,
      "questionText": "seeraa fi sirna kabajuun kan fayyadu",
      "imgUrl": ""
    },
    "optionA": {
      "id": "1",
      "hasImg": false,
      "ImgUrl": "",
      "optionText": "Balaa hirrisuuf"
    },
    "optionB": {
      "id": "2",
      "hasImg": false,
      "ImgUrl": "",
      "optionText": "Sochii tiraafikaa salphisu"
    },
    "optionC": {
      "id": "3",
      "hasImg": false,
      "ImgUrl": "",
      "optionText": "A fi B deebiidha"
    },
    "optionD": {
      "id": "4",
      "hasImg": false,
      "ImgUrl": "",
      "optionText": "Deebii hin qabu"
    },
    "answer": "3"
  },
  {
    "question": {
      "hasImg":false,
      "questionText": "Qabbaneesituu qileensa (AC) fayyidaan isaa kami",
      "imgUrl": ""
    },
    "optionA": {
      "id": "1",
      "hasImg": false,
      "ImgUrl": "",
      "optionText": "Qileensa gaabina keessa ni too'ata"
    },
    "optionB": {
      "id": "2",
      "hasImg": false,
      "ImgUrl": "",
      "optionText": "Miira laaqama hirrisa"
    },
    "optionC": {
      "id": "3",
      "hasImg": false,
      "ImgUrl": "",
      "optionText": "Hoo'a mootora hirrisa"
    },
    "optionD": {
      "id": "4",
      "hasImg": false,
      "ImgUrl": "",
      "optionText": " A fi B deebidha"
    },
    "answer": "1"
  }










  ]